pymd5search/__init__.py
pymd5search/args.py
pymd5search/pymd5search.py
pymd5search/update.py
pymd5search-0.0.2.dist-info/LICENSE.txt
pymd5search-0.0.2.dist-info/METADATA
pymd5search-0.0.2.dist-info/WHEEL
pymd5search-0.0.2.dist-info/entry_points.txt
pymd5search-0.0.2.dist-info/top_level.txt
pymd5search-0.0.2.dist-info/RECORD
