Metadata-Version: 2.1
Name: pymd5search
Version: 0.0.2
Summary: pymd5search loops and tries to find a string which equals to itself when encoded with the md5 hash function
Home-page: https://github.com/thib1984/pymd5search
Author: thib1984
Author-email: thibault.garcon@gmail.com
License: MIT
Platform: UNKNOWN
Classifier: Programming Language :: Python :: 3.6
Classifier: Programming Language :: Python :: 3.7
Classifier: Programming Language :: Python :: 3.8
Classifier: Programming Language :: Python :: 3.9
Classifier: Programming Language :: Python :: 3.10
Classifier: License :: OSI Approved :: MIT License
Classifier: Operating System :: OS Independent
Requires-Python: >=3.6
